{
  "_comment": "Demon-Corpse Mushroom — grows on battlefields in demonic regions. Canon (CANON_RI_ECOLOGY.md 2.3, Type C conf 3): 'Demon-Corpse Mushroom — Sky Demon / Fire Demon Country; grows on battlefields; demonic-aspect.' Custom block: ergenverse:demon_corpse_mushroom
  "type": "minecraft:flower",
  "config": {
    "feature": {
      "type": "minecraft:simple_block",
      "config": {
        "to_place": {
          "type": "minecraft:simple_state_provider",
          "state": {
            "Name": "ergenverse:demon_corpse_mushroom"
          }
        }
      }
    },
    "tries": 1,
    "xz_spread": 2,
    "y_spread": 0,
    "need_red_to_survive": false
  }
}
