{
  "_comment": "Faction relationships: dao_devil_sect. Per user directive: faction relationship network — allies/enemies/vassals/rivals. Prime Directive: relationships exist objectively.",
  "faction_id": "dao_devil_sect",
  "type": "sect",
  "allies": [],
  "enemies": [
    "wang_lin"
  ],
  "vassals": [],
  "rivals": [],
  "neutral": [],
  "note": "Annihilated by Wang Lin (canon-attested destruction)",
  "salt": 1095284495,
  "spiritual_vein_grade": {
    "grade": null,
    "element": null,
    "qi_modifier": null,
    "canon_note": "dao_devil_sect — spiritual vein grade not specified in canon"
  },
  "heritage_treasures": [],
  "_xianxia_schema": 2,
  "relationship_metadata": {
    "allies": [],
    "enemies": [
      {
        "id": "wang_lin",
        "strength": null,
        "since": null,
        "reason": null
      }
    ],
    "vassals": [],
    "rivals": [],
    "neutral": []
  }
}
