{
  "_comment": "Species: Ghost Face Beast (鬼面兽) from A Will Eternal. Canonical definition with all 13 fields per the Er Gen simulation spec. Prime Directive: Reality is objective; cultivation changes understanding, not existence. Every state described here exists independently of the player's perception.",
  "species_id": "ghost_face_beast",
  "name": "Ghost Face Beast",
  "nameCn": "鬼面兽",
  "novel": "A Will Eternal",
  "derivation_type": "B",
  "canon_confidence": 3,
  "canonical": {
    "appearance": "Beast 5 m, face is a screaming ghost, body shadow-wreathed",
    "size": "5 m adult, 2000 jin; ancient 15 m, 40000 jin",
    "behavior": "Hunts by fear; cultivates by consuming terror",
    "habitat": "Fear-aspected forbidden zones, ghost valleys",
    "cultivation": "Nascent Soul -> Spirit Severing (fear attribute)",
    "intelligence": 7,
    "diet": "fear, weaker beasts, lost cultivators",
    "relationships": "Lesser kin of Six-Desire Devil",
    "techniques": [
      "fear_roar",
      "ghost_face_display",
      "shadow_drain"
    ],
    "treasures": [
      "ghost_face_core",
      "fear_essence"
    ],
    "bloodline": "Ghost-Face lineage; fear-attribute bloodline",
    "mutations": [
      "true_fear_body"
    ],
    "ecology": "Inferred AFTER canonical fields; see ecosystem definitions.",
    "bloodline_tier": "ordinary_beast",
    "inner_dan_properties": {
      "has_core": false,
      "element": null,
      "grade": null,
      "alchemy_use": null,
      "canon_note": "ghost_face_beast — no specific inner dan documented in canon"
    },
    "hive_mind_anchor": {
      "is_hive": false,
      "queen_id": null,
      "swarm_id": null,
      "coordination": null,
      "canon_note": "ghost_face_beast — not a hive-mind species"
    },
    "combat_ai": "solo_ambush"
  },
  "art_direction": {
    "generator": "single canonical definition drives 10 life-state variants",
    "variants": [
      "juvenile",
      "adolescent",
      "adult",
      "ancient",
      "mutated",
      "injured",
      "starving",
      "tribulation_scarred",
      "corrupted",
      "enlightened"
    ],
    "note": "Per art-direction directive: build generators, not assets."
  },
  "salt": 864774398,
  "bloodline_tier": "spiritual",
  "inner_dan_properties": {
    "element": "neutral",
    "purity_tier": 3,
    "dao_resonance": "minor",
    "side_effects": []
  },
  "hive_mind_anchor": null,
  "_xianxia_schema": 2
}
