{
  "_comment": "Species: Spirit Fox (灵狐) from Renegade Immortal. Per user directive: every miscellaneous beast from RI must be accounted for and part of the ecosystem. Prime Directive: Reality is objective; cultivation changes understanding, not existence. Every being described here exists independently of the player's perception.",
  "species_id": "spirit_fox",
  "name": "Spirit Fox",
  "nameCn": "灵狐",
  "novel": "Renegade Immortal",
  "derivation_type": "B",
  "canon_confidence": 3,
  "canonical": {
    "appearance": "Elegant fox 1 m, fur shifts through spirit-colors, nine tails on ancient specimens",
    "size": "1 m adult, 30 jin; ancient 3 m, 500 jin",
    "behavior": "Cunning predator; cultivates by absorbing illusion-essence; uses illusions to hunt",
    "habitat": "Spirit forests, illusion-aspected valleys",
    "cultivation": "Foundation Establishment -> Core Formation (illusion attribute)",
    "intelligence": 7,
    "diet": "spirit rabbits, spirit herbs, smaller beasts",
    "relationships": "Rival of spirit cranes; preyed upon by mountain lions",
    "techniques": [
      "illusion_shift",
      "fox_charm",
      "spirit_dodge",
      "nine_tail_sweep"
    ],
    "treasures": [
      "spirit_fox_core",
      "fox_pelt",
      "illusion_essence"
    ],
    "bloodline": "Spirit-Fox lineage; illusion-attribute bloodline",
    "mutations": [
      "nine_tail",
      "true_fox_emperor"
    ],
    "ecology": "Integrated into RI ecosystem definitions; see ecosystem_integration.",
    "bloodline_tier": "spiritual_beast",
    "inner_dan_properties": {
      "has_core": false,
      "element": null,
      "grade": null,
      "alchemy_use": "No alchemy value — common beast with no condensed inner core",
      "canon_note": "spirit_fox — common beast, no condensed inner core"
    },
    "hive_mind_anchor": {
      "is_hive": false,
      "queen_id": null,
      "swarm_id": null,
      "coordination": null,
      "canon_note": "spirit_fox — not a hive-mind species"
    },
    "combat_ai": "solo_ambush"
  },
  "art_direction": {
    "generator": "single canonical definition drives 10 life-state variants",
    "variants": [
      "juvenile",
      "adolescent",
      "adult",
      "ancient",
      "mutated",
      "injured",
      "starving",
      "tribulation_scarred",
      "corrupted",
      "enlightened"
    ],
    "note": "Per art-direction directive: build generators, not assets."
  },
  "salt": 1987793329,
  "bloodline_tier": "ordinary",
  "inner_dan_properties": {
    "element": "illusion",
    "purity_tier": 2,
    "dao_resonance": "fox_charm",
    "side_effects": []
  },
  "hive_mind_anchor": null,
  "_xianxia_schema": 2
}
